views_partitioning/__init__.py
views_partitioning/data_partitioner.py
views_partitioning/legacy.py
views_partitioning/validation.py
views_partitioning-3.0.1.dist-info/WHEEL
views_partitioning-3.0.1.dist-info/METADATA
views_partitioning-3.0.1.dist-info/RECORD
