Metadata-Version: 2.1
Name: views-partitioning
Version: 3.0.1
Summary: 
Author: peder2911
Author-email: pglandsverk@gmail.com
Requires-Python: >=3.8,<4.0
Classifier: Programming Language :: Python :: 3
Classifier: Programming Language :: Python :: 3.10
Classifier: Programming Language :: Python :: 3.8
Classifier: Programming Language :: Python :: 3.9
Requires-Dist: pandas (>=1.3.3,<2.0.0)
Requires-Dist: toolz (>=0.11.1,<0.12.0)
Requires-Dist: views-schema (>=2.3.0,<3.0.0)
